{
    "dayz": 20,
    "is": 15,
    "a": 60,
    "multiplayer": 1,
    "online": 1,
    "survival": 2,
    "video": 3,
    "game": 41,
    "developed": 1,
    "and": 78,
    "published": 1,
    "by": 8,
    "bohemia": 7,
    "interactive": 6,
    "it": 12,
    "the": 195,
    "standalone": 4,
    "based": 4,
    "on": 31,
    "mod": 4,
    "of": 67,
    "same": 1,
    "name": 1,
    "for": 22,
    "arma": 4,
    "2": 4,
    "following": 3,
    "fiveyearlong": 1,
    "early": 6,
    "access": 6,
    "period": 1,
    "windows": 2,
    "was": 27,
    "officially": 3,
    "released": 12,
    "in": 49,
    "december": 3,
    "2018": 5,
    "xbox": 5,
    "one": 7,
    "playstation": 2,
    "4": 3,
    "2019": 5,
    "places": 1,
    "player": 14,
    "fictional": 3,
    "postsoviet": 1,
    "republic": 4,
    "chernarus": 5,
    "real": 2,
    "life": 2,
    "region": 1,
    "st": 1,
    "nad": 1,
    "labem": 1,
    "czech": 2,
    "original": 3,
    "setting": 1,
    "where": 4,
    "mysterious": 1,
    "plague": 1,
    "has": 4,
    "turned": 1,
    "most": 3,
    "population": 1,
    "into": 4,
    "violent": 1,
    "infected": 2,
    "as": 20,
    "survivor": 1,
    "must": 3,
    "scavenge": 2,
    "world": 5,
    "food": 4,
    "water": 3,
    "weapons": 3,
    "medicine": 1,
    "while": 3,
    "killing": 2,
    "or": 8,
    "avoiding": 2,
    "cooperating": 1,
    "with": 21,
    "other": 5,
    "players": 16,
    "an": 9,
    "effort": 1,
    "to": 56,
    "survive": 1,
    "outbreak": 2,
    "began": 2,
    "development": 22,
    "2012": 4,
    "when": 3,
    "mods": 2,
    "creator": 1,
    "dean": 3,
    "hall": 10,
    "joined": 1,
    "commence": 1,
    "work": 1,
    "version": 2,
    "been": 3,
    "focused": 3,
    "altering": 1,
    "engine": 5,
    "suit": 2,
    "games": 5,
    "needs": 1,
    "developing": 1,
    "working": 3,
    "clientserver": 2,
    "architecture": 3,
    "introducing": 1,
    "new": 11,
    "features": 6,
    "like": 1,
    "diseases": 2,
    "better": 2,
    "inventory": 1,
    "system": 4,
    "sold": 4,
    "over": 7,
    "three": 3,
    "million": 5,
    "copies": 5,
    "during": 5,
    "its": 5,
    "phase": 1,
    "gameplay": 3,
    "goal": 1,
    "stay": 1,
    "alive": 1,
    "healthy": 1,
    "conditions": 1,
    "zombie": 1,
    "that": 30,
    "have": 3,
    "befallen": 1,
    "ingame": 4,
    "spawns": 1,
    "random": 4,
    "area": 2,
    "usually": 1,
    "near": 1,
    "coast": 1,
    "equipped": 1,
    "only": 4,
    "simple": 1,
    "clothes": 1,
    "glow": 1,
    "stick": 1,
    "bandage": 1,
    "piece": 1,
    "fruit": 1,
    "begin": 2,
    "exploring": 1,
    "large": 4,
    "225": 1,
    "km2": 1,
    "87": 1,
    "sq": 1,
    "mi": 1,
    "landscape": 1,
    "former": 1,
    "soviet": 1,
    "investigate": 1,
    "locations": 1,
    "such": 9,
    "houses": 1,
    "barns": 1,
    "apartments": 1,
    "supplies": 4,
    "these": 4,
    "include": 2,
    "which": 8,
    "are": 14,
    "vital": 1,
    "prolonging": 1,
    "beyond": 1,
    "basics": 1,
    "can": 10,
    "find": 4,
    "various": 2,
    "forms": 1,
    "clothing": 6,
    "allow": 2,
    "customization": 1,
    "extra": 2,
    "storage": 1,
    "space": 1,
    "warmth": 1,
    "also": 10,
    "scattered": 2,
    "around": 3,
    "map": 9,
    "variety": 2,
    "allowing": 3,
    "protect": 1,
    "themselves": 1,
    "from": 6,
    "zombies": 1,
    "if": 5,
    "necessary": 1,
    "largely": 1,
    "range": 2,
    "melee": 1,
    "but": 3,
    "number": 4,
    "firearms": 4,
    "present": 2,
    "along": 1,
    "attachments": 1,
    "suppressors": 1,
    "telescopic": 1,
    "sights": 1,
    "dynamic": 1,
    "events": 2,
    "randomly": 1,
    "spawning": 3,
    "train": 1,
    "wrecks": 1,
    "police": 1,
    "situations": 1,
    "military": 1,
    "convoys": 1,
    "helicopter": 1,
    "crashes": 1,
    "contain": 2,
    "rare": 2,
    "equipment": 2,
    "not": 5,
    "be": 21,
    "found": 2,
    "elsewhere": 1,
    "additionally": 1,
    "gas": 5,
    "attacks": 1,
    "strike": 2,
    "areas": 3,
    "livonia": 4,
    "at": 10,
    "intervals": 1,
    "remaining": 2,
    "affected": 1,
    "zones": 4,
    "will": 7,
    "afflict": 1,
    "disease": 2,
    "causes": 2,
    "constant": 1,
    "bleeding": 2,
    "coughing": 1,
    "up": 3,
    "blood": 4,
    "vomiting": 1,
    "resulting": 3,
    "unconsciousness": 1,
    "death": 2,
    "unless": 1,
    "they": 3,
    "leave": 1,
    "suitable": 1,
    "medical": 2,
    "treatment": 1,
    "last": 2,
    "2040": 1,
    "minutes": 1,
    "before": 2,
    "fully": 3,
    "dissipating": 1,
    "may": 4,
    "use": 3,
    "nbc": 1,
    "mask": 1,
    "prevent": 1,
    "damage": 3,
    "there": 2,
    "two": 4,
    "permanent": 2,
    "contamination": 1,
    "each": 1,
    "containing": 1,
    "high": 1,
    "tier": 1,
    "exclusive": 1,
    "interaction": 1,
    "major": 1,
    "part": 2,
    "provides": 2,
    "proximity": 1,
    "voice": 1,
    "chat": 2,
    "text": 1,
    "gestures": 1,
    "waving": 1,
    "putting": 1,
    "hands": 1,
    "indicate": 1,
    "surrender": 1,
    "travelling": 1,
    "environment": 1,
    "poses": 1,
    "threats": 1,
    "their": 4,
    "characters": 1,
    "illnesses": 1,
    "currently": 1,
    "within": 2,
    "common": 2,
    "cold": 2,
    "cholera": 1,
    "kuru": 2,
    "salmonellosis": 1,
    "more": 4,
    "possible": 1,
    "cure": 1,
    "all": 4,
    "exception": 1,
    "shot": 1,
    "injured": 1,
    "items": 3,
    "person": 1,
    "damaged": 1,
    "bandaged": 1,
    "quickly": 1,
    "minimize": 1,
    "loss": 3,
    "excessive": 1,
    "result": 1,
    "serious": 1,
    "deterioration": 1,
    "vision": 1,
    "render": 1,
    "them": 1,
    "unconscious": 1,
    "able": 4,
    "hunt": 1,
    "animals": 6,
    "chickens": 1,
    "pigs": 1,
    "cows": 1,
    "deer": 1,
    "pose": 1,
    "threat": 1,
    "depending": 1,
    "hostile": 1,
    "attacked": 1,
    "wolves": 1,
    "spawn": 2,
    "packs": 1,
    "lone": 1,
    "grizzly": 1,
    "bear": 2,
    "remains": 1,
    "zone": 1,
    "long": 1,
    "enough": 1,
    "every": 2,
    "animal": 1,
    "skinned": 1,
    "meat": 2,
    "hides": 1,
    "bones": 1,
    "guts": 2,
    "except": 1,
    "chicken": 1,
    "instead": 2,
    "yield": 1,
    "feathers": 1,
    "hide": 2,
    "cooking": 1,
    "core": 1,
    "mechanic": 3,
    "cook": 1,
    "longer": 1,
    "preservation": 1,
    "times": 1,
    "safe": 1,
    "consumption": 1,
    "higher": 2,
    "nutritional": 1,
    "value": 1,
    "tan": 1,
    "turn": 1,
    "leather": 1,
    "crafting": 2,
    "includes": 1,
    "horticulture": 1,
    "option": 2,
    "both": 3,
    "harvest": 1,
    "wild": 1,
    "plants": 1,
    "grow": 1,
    "ones": 2,
    "own": 1,
    "crops": 1,
    "this": 4,
    "functional": 1,
    "base": 2,
    "building": 1,
    "allows": 1,
    "independent": 1,
    "structures": 2,
    "repurposing": 1,
    "alreadyexisting": 1,
    "vehicles": 2,
    "available": 4,
    "cut": 1,
    "down": 1,
    "time": 1,
    "needed": 2,
    "travel": 1,
    "provided": 1,
    "locate": 1,
    "restore": 2,
    "order": 4,
    "keep": 2,
    "tank": 1,
    "radiator": 1,
    "filled": 1,
    "huge": 1,
    "successes": 1,
    "announced": 6,
    "august": 3,
    "blog": 1,
    "would": 10,
    "conjunction": 1,
    "himself": 1,
    "project": 3,
    "lead": 1,
    "he": 6,
    "said": 3,
    "end": 1,
    "year": 2,
    "achieve": 1,
    "what": 3,
    "we": 2,
    "do": 1,
    "wanted": 3,
    "initial": 2,
    "release": 16,
    "november": 3,
    "running": 1,
    "branch": 1,
    "take": 1,
    "helicopters": 1,
    "virtuality": 1,
    "main": 1,
    "developmental": 2,
    "focus": 1,
    "critical": 1,
    "issues": 1,
    "bug": 2,
    "fixing": 1,
    "hacking": 1,
    "security": 1,
    "focuses": 1,
    "making": 3,
    "feel": 1,
    "realistic": 1,
    "increasing": 2,
    "enterable": 1,
    "buildings": 1,
    "stated": 4,
    "hopes": 1,
    "implement": 1,
    "bad": 1,
    "ideas": 1,
    "enjoy": 1,
    "rather": 2,
    "than": 4,
    "taking": 2,
    "no": 1,
    "risks": 1,
    "functions": 2,
    "item": 1,
    "npc": 1,
    "decided": 1,
    "server": 4,
    "machine": 1,
    "contrast": 1,
    "had": 7,
    "proportion": 1,
    "tasks": 2,
    "performed": 1,
    "client": 1,
    "doing": 1,
    "so": 1,
    "change": 1,
    "aims": 1,
    "reduce": 2,
    "hacks": 1,
    "exploits": 1,
    "removal": 1,
    "unnecessary": 1,
    "ai": 1,
    "flanking": 1,
    "via": 2,
    "digital": 1,
    "distribution": 1,
    "software": 1,
    "steam": 4,
    "browser": 1,
    "patching": 1,
    "functionality": 1,
    "troubled": 1,
    "similar": 1,
    "war": 1,
    "z": 1,
    "post": 1,
    "reddit": 1,
    "whole": 2,
    "saga": 1,
    "made": 2,
    "me": 1,
    "seriously": 1,
    "question": 1,
    "i": 1,
    "involved": 2,
    "industry": 1,
    "considered": 1,
    "leaving": 1,
    "missed": 1,
    "date": 4,
    "update": 6,
    "january": 1,
    "2013": 5,
    "saying": 1,
    "yet": 1,
    "because": 1,
    "developers": 3,
    "chance": 1,
    "go": 1,
    "just": 1,
    "improved": 1,
    "slightly": 1,
    "actually": 1,
    "redeveloping": 1,
    "way": 1,
    "dreamed": 1,
    "could": 1,
    "rescheduled": 1,
    "internal": 1,
    "closed": 1,
    "test": 1,
    "being": 5,
    "public": 1,
    "testing": 1,
    "place": 1,
    "until": 4,
    "finalized": 1,
    "june": 1,
    "commented": 2,
    "alpha": 10,
    "very": 2,
    "barebones": 2,
    "team": 8,
    "want": 1,
    "relatively": 1,
    "low": 1,
    "providing": 1,
    "reports": 1,
    "feedback": 1,
    "secondary": 1,
    "aim": 1,
    "funded": 1,
    "further": 1,
    "full": 1,
    "expects": 1,
    "beta": 1,
    "least": 1,
    "after": 4,
    "prior": 1,
    "were": 5,
    "network": 3,
    "optimizations": 1,
    "referred": 1,
    "bubble": 1,
    "load": 1,
    "loading": 1,
    "occur": 1,
    "vicinity": 1,
    "october": 1,
    "final": 2,
    "lap": 1,
    "100": 1,
    "percent": 1,
    "getting": 1,
    "out": 2,
    "door": 1,
    "focusing": 1,
    "performance": 1,
    "stability": 1,
    "adding": 1,
    "improving": 1,
    "controls": 1,
    "animations": 2,
    "among": 1,
    "things": 1,
    "throughout": 3,
    "posted": 1,
    "blogs": 1,
    "attended": 1,
    "conventions": 1,
    "uploaded": 1,
    "videos": 1,
    "keeping": 1,
    "community": 1,
    "progress": 2,
    "second": 2,
    "showed": 1,
    "animation": 1,
    "motion": 1,
    "capture": 1,
    "session": 1,
    "recording": 1,
    "well": 1,
    "some": 1,
    "interviews": 1,
    "third": 2,
    "contained": 1,
    "amount": 2,
    "footage": 1,
    "showing": 1,
    "march": 1,
    "2014": 4,
    "revealed": 2,
    "purchased": 2,
    "cauldron": 1,
    "studios": 1,
    "whose": 1,
    "25": 1,
    "added": 4,
    "gamescom": 3,
    "confirmed": 1,
    "ps4": 1,
    "console": 1,
    "determined": 1,
    "e3": 1,
    "2015": 1,
    "workshop": 1,
    "support": 1,
    "grants": 1,
    "host": 1,
    "servers": 1,
    "singleplayer": 1,
    "mode": 1,
    "future": 2,
    "106": 1,
    "introduced": 1,
    "fishing": 1,
    "official": 3,
    "landlocked": 1,
    "polishspeaking": 1,
    "country": 1,
    "off": 1,
    "including": 2,
    "topography": 1,
    "climate": 2,
    "originally": 1,
    "dlc": 1,
    "costing": 1,
    "30": 1,
    "later": 1,
    "free": 1,
    "owned": 1,
    "price": 5,
    "increase": 1,
    "4999": 1,
    "40": 1,
    "2022": 2,
    "uk": 1,
    "production": 1,
    "companies": 1,
    "bought": 1,
    "film": 2,
    "rights": 1,
    "create": 1,
    "feature": 1,
    "adaptation": 1,
    "2024": 1,
    "frostline": 2,
    "sakhal": 3,
    "itself": 1,
    "included": 1,
    "greater": 1,
    "emphasis": 1,
    "temperatures": 1,
    "effect": 1,
    "reworking": 1,
    "heat": 1,
    "comfort": 1,
    "ability": 1,
    "become": 2,
    "frozen": 2,
    "inedible": 1,
    "thawed": 1,
    "too": 1,
    "hot": 2,
    "eat": 1,
    "upon": 1,
    "attempting": 1,
    "character": 1,
    "certain": 2,
    "given": 1,
    "variants": 1,
    "differing": 1,
    "insulation": 3,
    "style": 1,
    "snoworiented": 1,
    "camouflage": 1,
    "patterns": 1,
    "livonias": 1,
    "loot": 1,
    "economy": 1,
    "altered": 1,
    "summer": 1,
    "lower": 1,
    "remained": 1,
    "mix": 1,
    "warmer": 1,
    "lighter": 1,
    "reworked": 1,
    "stages": 1,
    "pneumonia": 2,
    "continual": 1,
    "health": 2,
    "ignored": 1,
    "heavy": 1,
    "metal": 1,
    "poisoning": 1,
    "contracted": 1,
    "consuming": 1,
    "unfiltered": 1,
    "snow": 1,
    "ground": 1,
    "hare": 1,
    "fox": 1,
    "reindeer": 1,
    "set": 1,
    "volcanic": 1,
    "polar": 1,
    "archipelago": 1,
    "heavily": 1,
    "wooded": 1,
    "ice": 1,
    "sheets": 1,
    "surround": 1,
    "ocean": 1,
    "island": 1,
    "wells": 1,
    "replaced": 1,
    "springs": 2,
    "maps": 1,
    "villages": 1,
    "first": 2,
    "publicly": 1,
    "build": 2,
    "16": 1,
    "stage": 1,
    "through": 1,
    "steams": 2,
    "program": 1,
    "cheaper": 1,
    "increased": 1,
    "127": 1,
    "still": 1,
    "targeting": 1,
    "audience": 1,
    "who": 1,
    "called": 1,
    "experience": 1,
    "platform": 1,
    "preview": 1,
    "29": 1,
    "13": 1,
    "reception": 1,
    "172500": 1,
    "24": 1,
    "hours": 1,
    "totalling": 1,
    "us5": 1,
    "sales": 4,
    "peak": 2,
    "200": 1,
    "per": 1,
    "minute": 1,
    "week": 1,
    "400000": 1,
    "reached": 1,
    "total": 1,
    "top": 1,
    "charts": 1,
    "weeks": 1,
    "row": 1,
    "review": 1,
    "rick": 1,
    "lane": 1,
    "eurogamer": 1,
    "positively": 1,
    "additions": 1,
    "worth": 2,
    "current": 1,
    "hand": 1,
    "craig": 1,
    "pearson": 1,
    "pc": 1,
    "gamer": 1,
    "good": 1,
    "experiences": 1,
    "already": 1,
    "four": 1,
    "april": 1,
    "beat": 1,
    "alltime": 1,
    "record": 1,
    "50000": 1,
    "count": 1,
    "briefly": 1,
    "banned": 1,
    "australia": 1,
    "due": 1,
    "illicit": 1,
    "proscribed": 1,
    "drug": 1,
    "related": 1,
    "incentives": 1,
    "rewards": 1,
    "derived": 1,
    "options": 1,
    "cannabis": 1,
    "joint": 1,
    "communitymade": 1,
    "ban": 1,
    "eventually": 1,
    "lifted": 1,
    "edited": 1,
    "comply": 1,
    "australian": 1,
    "classification": 1,
    "board": 1,
    "awards": 4,
    "won": 3,
    "mmorpgcom": 1,
    "award": 2,
    "best": 3,
    "hybrid": 1,
    "mmo": 1,
    "pax": 1,
    "east": 1,
    "winner": 1,
    "igns": 1,
    "peoples": 1,
    "choice": 1,
    "beating": 1,
    "49": 1,
    "15": 1,
    "votes": 1,
    "golden": 1,
    "joystick": 1,
    "indie": 1,
    "friends": 1,
    "category": 1,
    "references": 1,
    "external": 1,
    "links": 1,
    "website": 1
}