{
    "gran": 2,
    "turismo": 2,
    "6": 2,
    "pal": 1,
    "version": 1,
    "cover": 1,
    "art": 1,
    "developers": 1,
    "polyphony": 1,
    "digital": 1,
    "publishers": 1,
    "sony": 1,
    "computer": 1,
    "entertainment": 1,
    "directors": 1,
    "kazunori": 2,
    "yamauchi": 2,
    "producers": 1,
    "series": 1,
    "platforms": 1,
    "playstation": 1,
    "3": 1,
    "release": 1,
    "ww": 1,
    "december": 1,
    "2013": 1,
    "genres": 1,
    "sim": 1,
    "racing": 1,
    "modes": 1,
    "singleplayer": 1,
    "multiplayer": 1
}