{
    "3d": 1,
    "modeling": 1,
    "agent": 1,
    "video": 17,
    "game": 18,
    "allgame": 1,
    "automotive": 2,
    "lighting": 1,
    "beaterator": 1,
    "body": 1,
    "kit": 1,
    "bully": 1,
    "christian": 1,
    "cantamessa": 1,
    "computing": 1,
    "platform": 1,
    "dan": 1,
    "houser": 2,
    "discogs": 1,
    "edge": 1,
    "magazine": 4,
    "electronic": 2,
    "entertainment": 2,
    "expo": 1,
    "gaming": 2,
    "monthly": 1,
    "weekly": 1,
    "eurogamer": 1,
    "europe": 1,
    "gale": 1,
    "research": 1,
    "gamepro": 1,
    "gamerevolution": 1,
    "gamespot": 1,
    "gamespy": 1,
    "informer": 1,
    "revolution": 1,
    "grand": 1,
    "theft": 1,
    "auto": 1,
    "hud": 1,
    "headlamp": 1,
    "hood": 1,
    "scoop": 1,
    "ign": 1,
    "import": 1,
    "scene": 1,
    "insignia": 1,
    "xbox": 4,
    "internet": 1,
    "archive": 1,
    "irrversible": 1,
    "soundtrack": 1,
    "ken": 2,
    "griffey": 2,
    "jrs": 1,
    "slugfest": 1,
    "la": 2,
    "noire": 2,
    "lazlow": 1,
    "jones": 1,
    "leslie": 1,
    "benzies": 1,
    "list": 1,
    "of": 2,
    "games": 4,
    "published": 1,
    "by": 1,
    "rockstar": 15,
    "los": 2,
    "angeles": 2,
    "major": 1,
    "league": 1,
    "baseball": 1,
    "featuring": 1,
    "jr": 1,
    "manhunt": 2,
    "2": 5,
    "max": 1,
    "payne": 1,
    "maxim": 1,
    "metacritic": 1,
    "microsoft": 1,
    "windows": 1,
    "midnight": 5,
    "club": 5,
    "street": 2,
    "racing": 3,
    "3": 2,
    "dub": 2,
    "edition": 2,
    "midtown": 2,
    "madness": 2,
    "mobygames": 1,
    "multiplayer": 1,
    "music": 4,
    "north": 2,
    "america": 1,
    "official": 2,
    "us": 1,
    "playstation": 2,
    "open": 2,
    "world": 1,
    "pc": 1,
    "gamer": 1,
    "paris": 2,
    "catacombs": 1,
    "personal": 1,
    "computer": 1,
    "playboy": 1,
    "rap": 1,
    "red": 3,
    "dead": 3,
    "redemption": 1,
    "revolver": 1,
    "advanced": 1,
    "engine": 1,
    "dundee": 1,
    "presents": 1,
    "table": 1,
    "tennis": 1,
    "india": 1,
    "leeds": 1,
    "lincoln": 1,
    "london": 1,
    "new": 1,
    "england": 1,
    "san": 1,
    "diego": 1,
    "toronto": 1,
    "vancouver": 1,
    "vienna": 1,
    "sam": 1,
    "seine": 1,
    "singleplayer": 1,
    "smugglers": 2,
    "run": 2,
    "spoiler": 1,
    "spyhunter": 1,
    "taketwo": 1,
    "interactive": 1,
    "techno": 1,
    "test": 1,
    "drive": 1,
    "offroad": 1,
    "wide": 1,
    "the": 4,
    "football": 1,
    "factory": 1,
    "film": 1,
    "hollywood": 1,
    "reporter": 1,
    "village": 1,
    "voice": 1,
    "warriors": 1,
    "thomas": 1,
    "bangalter": 1,
    "tokyo": 1,
    "trance": 1,
    "transworld": 1,
    "surf": 1,
    "undead": 1,
    "nightmare": 1,
    "artist": 1,
    "creative": 1,
    "director": 1,
    "designer": 1,
    "developer": 1,
    "genre": 1,
    "producer": 1,
    "programmer": 1,
    "publisher": 1,
    "writer": 1,
    "console": 1,
    "network": 1,
    "youtube": 1
}