{
    "1001": 1,
    "video": 41,
    "games": 16,
    "you": 2,
    "must": 1,
    "play": 1,
    "before": 1,
    "die": 1,
    "1upcom": 1,
    "3d": 3,
    "computer": 2,
    "graphics": 1,
    "modeling": 1,
    "3rd": 1,
    "annual": 1,
    "interactive": 2,
    "achievement": 2,
    "awards": 2,
    "4kids": 1,
    "entertainment": 3,
    "6th": 1,
    "blockbuster": 1,
    "aol": 1,
    "actionadventure": 1,
    "action": 1,
    "game": 39,
    "adventures": 1,
    "of": 17,
    "sonic": 102,
    "the": 54,
    "hedgehog": 33,
    "allgame": 1,
    "all": 1,
    "media": 4,
    "network": 2,
    "amy": 1,
    "rose": 1,
    "angry": 1,
    "birds": 1,
    "anime": 1,
    "anthropomorphism": 1,
    "apple": 1,
    "inc": 2,
    "archie": 2,
    "comics": 2,
    "astro": 1,
    "boy": 2,
    "2004": 1,
    "australasia": 1,
    "big": 1,
    "cat": 1,
    "billy": 1,
    "hatcher": 1,
    "and": 4,
    "giant": 1,
    "egg": 1,
    "boss": 2,
    "fight": 1,
    "bradygames": 1,
    "brave": 1,
    "wave": 1,
    "productions": 1,
    "burning": 1,
    "rangers": 1,
    "cbs": 1,
    "cpu": 1,
    "cancn": 1,
    "chao": 1,
    "chaos": 3,
    "character": 4,
    "emeralds": 1,
    "characters": 2,
    "chuchu": 1,
    "rocket": 1,
    "collision": 1,
    "detection": 1,
    "computing": 2,
    "platform": 2,
    "crash": 1,
    "bandicoot": 1,
    "craveonline": 1,
    "crush": 1,
    "40": 1,
    "curse": 1,
    "dice": 1,
    "award": 1,
    "for": 1,
    "outstanding": 1,
    "technical": 2,
    "dic": 1,
    "destructoid": 1,
    "doctor": 3,
    "eggman": 1,
    "ivo": 1,
    "robotnik": 2,
    "downloadable": 1,
    "content": 1,
    "dr": 1,
    "robotniks": 1,
    "mean": 1,
    "bean": 1,
    "machine": 1,
    "dreamcast": 2,
    "collection": 5,
    "e102": 1,
    "gamma": 1,
    "e3": 1,
    "2000": 1,
    "echidna": 2,
    "edge": 1,
    "magazine": 5,
    "educational": 1,
    "in": 2,
    "series": 3,
    "electronic": 1,
    "gaming": 5,
    "monthly": 1,
    "electropop": 1,
    "eurogamer": 1,
    "europe": 1,
    "fall": 1,
    "guys": 1,
    "feel": 1,
    "magic": 1,
    "xyxx": 1,
    "fighters": 2,
    "megamix": 1,
    "fighting": 1,
    "fishing": 1,
    "rod": 1,
    "flicky": 1,
    "frame": 1,
    "rate": 1,
    "fullmotion": 1,
    "funk": 1,
    "future": 3,
    "publishing": 3,
    "us": 1,
    "plc": 2,
    "gamasutra": 1,
    "gamecube": 1,
    "gamepro": 1,
    "gamerankings": 1,
    "gamespot": 1,
    "gamestop": 1,
    "advance": 4,
    "gear": 1,
    "informer": 1,
    "revolution": 2,
    "engine": 1,
    "gamer": 2,
    "gamesmaster": 1,
    "gamesradar": 2,
    "gamestm": 1,
    "glitch": 1,
    "green": 1,
    "hill": 1,
    "zone": 1,
    "guatemala": 1,
    "hardline": 1,
    "band": 1,
    "hayao": 1,
    "nakayama": 1,
    "health": 1,
    "hepburn": 1,
    "romanization": 1,
    "highdefinition": 1,
    "hirokazu": 1,
    "yasuhara": 1,
    "hollywood": 1,
    "hyper": 1,
    "ign": 1,
    "isbn": 1,
    "identifier": 2,
    "issn": 1,
    "itunes": 1,
    "ica": 1,
    "peru": 2,
    "imagine": 1,
    "international": 2,
    "data": 1,
    "group": 1,
    "invincibility": 1,
    "japan": 1,
    "japanese": 1,
    "language": 1,
    "johnny": 1,
    "gioeli": 1,
    "jon": 1,
    "st": 1,
    "john": 1,
    "joystiq": 1,
    "junichi": 1,
    "kanemaru": 1,
    "jun": 1,
    "senoue": 1,
    "kazuyuki": 1,
    "hoshino": 1,
    "knuckles": 3,
    "chaotix": 1,
    "kotaku": 1,
    "launch": 1,
    "lego": 1,
    "dimensions": 1,
    "level": 1,
    "life": 3,
    "list": 9,
    "team": 5,
    "features": 1,
    "printed": 1,
    "xbox": 6,
    "360": 2,
    "compatible": 1,
    "with": 1,
    "one": 2,
    "commercial": 1,
    "failures": 1,
    "unofficial": 1,
    "considered": 1,
    "best": 1,
    "looney": 1,
    "tunes": 1,
    "machu": 1,
    "picchu": 1,
    "mad": 1,
    "scientist": 1,
    "mario": 7,
    "at": 6,
    "london": 1,
    "2012": 1,
    "olympic": 6,
    "tokyo": 2,
    "2020": 1,
    "winter": 2,
    "rio": 1,
    "2016": 1,
    "sochi": 1,
    "2014": 1,
    "masaru": 1,
    "setsumaru": 1,
    "master": 1,
    "emerald": 1,
    "mesoamerica": 1,
    "metacritic": 1,
    "metal": 1,
    "michael": 1,
    "mcgaharn": 1,
    "microsoft": 1,
    "miles": 1,
    "tails": 4,
    "prower": 1,
    "minigame": 1,
    "multiplayer": 1,
    "music": 2,
    "naoto": 1,
    "ohshima": 1,
    "next": 1,
    "generation": 2,
    "nights": 2,
    "journey": 1,
    "dreams": 2,
    "into": 1,
    "nintendo": 4,
    "3ds": 1,
    "64": 2,
    "nonplayer": 1,
    "north": 1,
    "america": 1,
    "official": 1,
    "onrails": 1,
    "shooter": 1,
    "original": 1,
    "animation": 1,
    "overworld": 1,
    "pal": 1,
    "region": 1,
    "pacman": 1,
    "panzer": 1,
    "dragoon": 1,
    "patch": 1,
    "phantasy": 5,
    "star": 5,
    "online": 2,
    "episode": 3,
    "iii": 1,
    "card": 1,
    "portable": 1,
    "universe": 2,
    "pinball": 2,
    "playstation": 1,
    "3": 3,
    "player": 1,
    "polygon": 1,
    "website": 1,
    "porting": 1,
    "powerup": 1,
    "pressreader": 1,
    "product": 1,
    "bundling": 1,
    "proprietary": 1,
    "software": 1,
    "puyo": 16,
    "pop": 2,
    "fever": 3,
    "20th": 1,
    "anniversary": 2,
    "15th": 1,
    "7": 1,
    "2": 9,
    "tetris": 2,
    "ram": 1,
    "racing": 5,
    "rayman": 1,
    "great": 1,
    "escape": 1,
    "realvideo": 1,
    "reboot": 1,
    "fiction": 1,
    "replay": 1,
    "value": 1,
    "retro": 1,
    "rings": 2,
    "rock": 2,
    "n": 1,
    "roll": 1,
    "roleplaying": 1,
    "ryan": 1,
    "drummond": 1,
    "sakura": 1,
    "wars": 1,
    "2019": 1,
    "samba": 1,
    "de": 1,
    "amigo": 1,
    "sandboarding": 1,
    "sega": 8,
    "segasonic": 1,
    "genesis": 2,
    "heroes": 2,
    "saturn": 1,
    "superstars": 3,
    "tennis": 1,
    "institute": 1,
    "shadow": 3,
    "generations": 2,
    "shoot": 1,
    "em": 1,
    "up": 1,
    "shun": 1,
    "nakamura": 1,
    "siliconera": 1,
    "singleplayer": 1,
    "sixth": 1,
    "consoles": 1,
    "sonics": 1,
    "ultimate": 1,
    "allstars": 2,
    "transformed": 1,
    "blast": 2,
    "adventure": 5,
    "battle": 1,
    "boom": 3,
    "fire": 1,
    "ice": 1,
    "rise": 1,
    "lyric": 1,
    "shattered": 1,
    "crystal": 1,
    "cd": 1,
    "chronicles": 1,
    "dark": 1,
    "brotherhood": 1,
    "classic": 1,
    "colors": 1,
    "dash": 1,
    "dream": 1,
    "drift": 2,
    "extreme": 1,
    "forces": 1,
    "free": 1,
    "riders": 3,
    "frontiers": 1,
    "gems": 1,
    "jam": 1,
    "jump": 2,
    "labyrinth": 1,
    "lost": 1,
    "world": 1,
    "mania": 1,
    "mega": 1,
    "origins": 1,
    "party": 1,
    "r": 1,
    "crossworlds": 1,
    "zero": 1,
    "gravity": 1,
    "rivals": 2,
    "rumble": 1,
    "runners": 2,
    "rush": 2,
    "shuffle": 1,
    "speed": 1,
    "simulator": 1,
    "spinball": 1,
    "usa": 1,
    "underground": 1,
    "unleashed": 1,
    "x": 1,
    "xtreme": 1,
    "black": 1,
    "knight": 1,
    "secret": 1,
    "triple": 1,
    "trouble": 1,
    "1991": 1,
    "2006": 1,
    "8bit": 2,
    "ova": 1,
    "film": 1,
    "4": 2,
    "i": 1,
    "ii": 1,
    "pocket": 1,
    "soulcalibur": 1,
    "spotify": 1,
    "steam": 1,
    "service": 1,
    "studio": 1,
    "pierrot": 1,
    "super": 4,
    "monkey": 1,
    "ball": 1,
    "smash": 1,
    "bros": 1,
    "skypatrol": 1,
    "takashi": 1,
    "iizuka": 1,
    "designer": 2,
    "tamagotchi": 1,
    "ted": 1,
    "poley": 1,
    "texture": 1,
    "mapping": 1,
    "av": 1,
    "club": 1,
    "legend": 1,
    "zelda": 1,
    "murder": 1,
    "rub": 1,
    "rabbits": 1,
    "tikal": 1,
    "title": 1,
    "screen": 1,
    "forum": 1,
    "tomoya": 1,
    "ohtani": 1,
    "tony": 1,
    "harnell": 1,
    "ubm": 1,
    "usgamer": 1,
    "ulalas": 1,
    "channel": 1,
    "j": 1,
    "unreal": 1,
    "tournament": 1,
    "1999": 1,
    "unreleased": 1,
    "valve": 1,
    "corporation": 1,
    "variety": 1,
    "artist": 1,
    "composer": 1,
    "console": 1,
    "emulator": 1,
    "creative": 1,
    "director": 1,
    "developer": 1,
    "genre": 1,
    "industry": 1,
    "producer": 1,
    "programmer": 1,
    "publisher": 1,
    "remake": 1,
    "writer": 1,
    "vinyl": 1,
    "lp": 1,
    "virtual": 2,
    "camera": 1,
    "system": 1,
    "pet": 1,
    "visual": 1,
    "memory": 1,
    "unit": 1,
    "voice": 1,
    "acting": 1,
    "voodoo2": 1,
    "vox": 1,
    "walt": 1,
    "disney": 1,
    "widescreen": 1,
    "windows": 1,
    "marketplace": 1,
    "xs": 1,
    "yuji": 2,
    "naka": 1,
    "uekawa": 1,
    "ziff": 1,
    "davis": 1
}