{
    "bully": 1,
    "ntsc": 1,
    "cover": 1,
    "art": 1,
    "for": 1,
    "playstation": 3,
    "2": 3,
    "developers": 1,
    "rockstar": 2,
    "vancouver": 1,
    "a": 1,
    "publishers": 1,
    "games": 1,
    "producers": 1,
    "jeronimo": 1,
    "barrera": 1,
    "steve": 1,
    "martin": 1,
    "designers": 1,
    "mike": 2,
    "skupa": 1,
    "sergei": 1,
    "kuprejanov": 1,
    "programmers": 1,
    "slett": 1,
    "peter": 1,
    "grant": 1,
    "artists": 1,
    "steven": 1,
    "olds": 1,
    "writers": 1,
    "dan": 1,
    "houser": 1,
    "jacob": 1,
    "krarup": 1,
    "composers": 1,
    "shawn": 1,
    "lee": 1,
    "engine": 1,
    "renderware": 1,
    "gamebryo": 1,
    "b": 1,
    "platforms": 1,
    "wii": 2,
    "xbox": 2,
    "360": 2,
    "windows": 2,
    "android": 2,
    "ios": 2,
    "release": 1,
    "17": 2,
    "october": 5,
    "2006": 4,
    "na": 2,
    "eu": 1,
    "25": 1,
    "au": 1,
    "27": 1,
    "4": 1,
    "march": 2,
    "2008": 3,
    "pal": 1,
    "7": 1,
    "ww": 2,
    "21": 1,
    "8": 1,
    "december": 1,
    "2016": 1,
    "genres": 1,
    "actionadventure": 1,
    "modes": 1,
    "singleplayer": 1,
    "multiplayer": 1,
    "c": 1
}